trssapi/__init__.py
trssapi/base.py
trssapi/skins.py
trssapi/users.py
trssapi-0.0.2.dist-info/METADATA
trssapi-0.0.2.dist-info/WHEEL
trssapi-0.0.2.dist-info/licenses/LICENSE
trssapi-0.0.2.dist-info/RECORD
