Metadata-Version: 2.4
Name: trssapi
Version: 0.0.2
Summary: Simple module for interaction with Team Run Skin Storage database.
Project-URL: Homepage, https://github.com/tttpm/py-trss-api
Author-email: tttpm <tttttttttpm@gmail.com>
License-Expression: MIT
License-File: LICENSE
Classifier: Operating System :: OS Independent
Classifier: Programming Language :: Python :: 3
Requires-Python: >=3.6
Requires-Dist: requests
